setup.py
jdcloud_function_mock.egg-info/PKG-INFO
jdcloud_function_mock.egg-info/SOURCES.txt
jdcloud_function_mock.egg-info/dependency_links.txt
jdcloud_function_mock.egg-info/requires.txt
jdcloud_function_mock.egg-info/top_level.txt
jdcloud_mock/__init__.py
jdcloud_mock/jdcloud_apim_mock.py