Metadata-Version: 1.0
Name: jdcloud-function-mock
Version: 0.1.0
Summary: JDCloud Function Local Mock
Home-page: UNKNOWN
Author: JDCloud Middleware Team
Author-email: UNKNOWN
License: Apache License V2.0
Platform: UNKNOWN
